[
    {
        "nombre": "LOLITA",
        "puntaje": 325,
        "fecha": "25/11/2024"
    },
    {
        "nombre": "LIONEL",
        "puntaje": 125,
        "fecha": "25/11/2024"
    },
    {
        "nombre": "PEPE",
        "puntaje": 325,
        "fecha": "25/11/2024"
    },
    {
        "nombre": "PEPE",
        "puntaje": 325,
        "fecha": "25/11/2024"
    },
    {
        "nombre": "PEPE",
        "puntaje": 0,
        "fecha": "25/11/2024"
    },
    {
        "nombre": "PEPE",
        "puntaje": 50,
        "fecha": "25/11/2024"
    },
    {
        "nombre": "PEPE",
        "puntaje": 325,
        "fecha": "25/11/2024"
    },
    {
        "nombre": "JEJE",
        "puntaje": 250,
        "fecha": "25/11/2024"
    },
    {
        "nombre": "ASDASD",
        "puntaje": 450,
        "fecha": "25/11/2024"
    },
    {
        "nombre": "PEPE",
        "puntaje": 0,
        "fecha": "25/11/2024"
    },
    {
        "nombre": "JUJUY",
        "puntaje": 800,
        "fecha": "25/11/2024"
    },
    {
        "nombre": "PEPE",
        "puntaje": 500,
        "fecha": "25/11/2024"
    },
    {
        "nombre": "LIONEL",
        "puntaje": 700,
        "fecha": "25/11/2024"
    }
]